Workbook

Sheet Raw Data
A1: 📊 SALES TRANSACTIONS — RAW DATASET (2024 Q1–Q2)
A2: OrderID | B2: Date | C2: SalesRep | D2: Region | E2: Category | F2: Product | G2: Units | H2: UnitPrice | I2: Discount | J2: CustomerType | K2: ReturnFlag
A3: ORD-001 | B3: 2024-01-05 | C3: Alice | D3: North | E3: Electronics | F3: Laptop Pro | G3: 2 | H3: 1299.99 | I3: 0.05 | J3: Business | K3: N
A4: ORD-002 | B4: 2024-01-08 | C4: Bob | D4: South | E4: Furniture | F4: Desk Chair | G4: 5 | H4: 349.5 | I4: 0.1 | J4: Retail | K4: N
A5: ORD-003 | B5: 2024-01-12 | C5: Carol | D5: East | E5: Electronics | F5: Tablet X | G5: 3 | H5: 499 | I5: 0 | J5: Business | K5: N
A6: ORD-004 | B6: 2024-01-15 | C6: Alice | D6: North | E6: Office Supplies | F6: Notebooks | G6: 50 | H6: 4.99 | I6: 0.15 | J6: Retail | K6: N
A7: ORD-005 | B7: 2024-01-20 | C7: Dave | D7: West | E7: Electronics | F7: Smartphone Z | G7: 4 | H7: 899 | I7: 0.05 | J7: Business | K7: N
A8: ORD-006 | B8: 2024-01-22 | C8: Bob | D8: South | E8: Furniture | F8: Standing Desk | G8: 2 | H8: 699 | I8: 0.1 | J8: Business | K8: N
A9: ORD-007 | B9: 2024-01-28 | C9: Eve | D9: North | E9: Office Supplies | F9: Pens (Box) | G9: 30 | H9: 12.5 | I9: 0 | J9: Retail | K9: N
A10: ORD-008 | B10: 2024-02-03 | C10: Carol | D10: East | E10: Electronics | F10: Monitor 27" | G10: 6 | H10: 429.99 | I10: 0.05 | J10: Business | K10: N
A11: ORD-009 | B11: 2024-02-07 | C11: Alice | D11: North | E11: Furniture | F11: Bookshelf | G11: 3 | H11: 189 | I11: 0 | J11: Retail | K11: N
A12: ORD-010 | B12: 2024-02-10 | C12: Dave | D12: West | E12: Electronics | F12: Laptop Pro | G12: 1 | H12: 1299.99 | I12: 0.1 | J12: Business | K12: N
A13: ORD-011 | B13: 2024-02-14 | C13: Bob | D13: South | E13: Office Supplies | F13: Stapler | G13: 15 | H13: 8.99 | I13: 0 | J13: Retail | K13: N
A14: ORD-012 | B14: 2024-02-18 | C14: Eve | D14: North | E14: Electronics | F14: Tablet X | G14: 2 | H14: 499 | I14: 0.05 | J14: Business | K14: N
... A42: ORD-040 | B42: 2024-06-14 | C42: Dave | D42: West | E42: Electronics | F42: Smartphone Z | G42: 5 | H42: 899 | I42: 0.1 | J42: Business | K42: N

Sheet Cleaned Data
A1: ✅ CLEANED & ENRICHED DATASET — Derived columns added
A2: OrderID | B2: Date | C2: Month | D2: Quarter | E2: SalesRep | F2: Region | G2: Category | H2: Product | I2: Units | J2: UnitPrice | K2: Discount | L2: GrossSales | M2: DiscountAmt | N2: NetSales | O2: CustomerType | P2: ReturnFlag | Q2: IsReturn
A3: ORD-001 | B3: 45296 | C3: Jan | D3: Q1 | E3: Alice | F3: North | G3: Electronics | H3: Laptop Pro | I3: 2 | J3: 1299.99 | K3: 0.05 | L3: =I3*J3 -> 2599.98 | M3: =L3*K3 -> 129.999 | N3: =L3-M3 -> 2469.981 | O3: Business | P3: N | Q3: =IF(P3="Y",1,0) -> 0
A4: ORD-002 | B4: 45299 | C4: Jan | D4: Q1 | E4: Bob | F4: South | G4: Furniture | H4: Desk Chair | I4: 5 | J4: 349.5 | K4: 0.1 | L4: =I4*J4 -> 1747.5 | M4: =L4*K4 -> 174.75 | N4: =L4-M4 -> 1572.75 | O4: Retail | P4: N | Q4: =IF(P4="Y",1,0) -> 0
A5: ORD-003 | B5: 45303 | C5: Jan | D5: Q1 | E5: Carol | F5: East | G5: Electronics | H5: Tablet X | I5: 3 | J5: 499 | K5: 0 | L5: =I5*J5 -> 1497 | M5: =L5*K5 -> 0 | N5: =L5-M5 -> 1497 | O5: Business | P5: N | Q5: =IF(P5="Y",1,0) -> 0
A6: ORD-004 | B6: 45306 | C6: Jan | D6: Q1 | E6: Alice | F6: North | G6: Office Supplies | H6: Notebooks | I6: 50 | J6: 4.99 | K6: 0.15 | L6: =I6*J6 -> 249.5 | M6: =L6*K6 -> 37.425 | N6: =L6-M6 -> 212.075 | O6: Retail | P6: N | Q6: =IF(P6="Y",1,0) -> 0
A7: ORD-005 | B7: 45311 | C7: Jan | D7: Q1 | E7: Dave | F7: West | G7: Electronics | H7: Smartphone Z | I7: 4 | J7: 899 | K7: 0.05 | L7: =I7*J7 -> 3596 | M7: =L7*K7 -> 179.8 | N7: =L7-M7 -> 3416.2 | O7: Business | P7: N | Q7: =IF(P7="Y",1,0) -> 0
A8: ORD-006 | B8: 45313 | C8: Jan | D8: Q1 | E8: Bob | F8: South | G8: Furniture | H8: Standing Desk | I8: 2 | J8: 699 | K8: 0.1 | L8: =I8*J8 -> 1398 | M8: =L8*K8 -> 139.8 | N8: =L8-M8 -> 1258.2 | O8: Business | P8: N | Q8: =IF(P8="Y",1,0) -> 0
A9: ORD-007 | B9: 45319 | C9: Jan | D9: Q1 | E9: Eve | F9: North | G9: Office Supplies | H9: Pens (Box) | I9: 30 | J9: 12.5 | K9: 0 | L9: =I9*J9 -> 375 | M9: =L9*K9 -> 0 | N9: =L9-M9 -> 375 | O9: Retail | P9: N | Q9: =IF(P9="Y",1,0) -> 0
A10: ORD-008 | B10: 45325 | C10: Feb | D10: Q1 | E10: Carol | F10: East | G10: Electronics | H10: Monitor 27" | I10: 6 | J10: 429.99 | K10: 0.05 | L10: =I10*J10 -> 2579.94 | M10: =L10*K10 -> 128.997 | N10: =L10-M10 -> 2450.943 | O10: Business | P10: N | Q10: =IF(P10="Y",1,0) -> 0
A11: ORD-009 | B11: 45329 | C11: Feb | D11: Q1 | E11: Alice | F11: North | G11: Furniture | H11: Bookshelf | I11: 3 | J11: 189 | K11: 0 | L11: =I11*J11 -> 567 | M11: =L11*K11 -> 0 | N11: =L11-M11 -> 567 | O11: Retail | P11: N | Q11: =IF(P11="Y",1,0) -> 0
A12: ORD-010 | B12: 45332 | C12: Feb | D12: Q1 | E12: Dave | F12: West | G12: Electronics | H12: Laptop Pro | I12: 1 | J12: 1299.99 | K12: 0.1 | L12: =I12*J12 -> 1299.99 | M12: =L12*K12 -> 129.999 | N12: =L12-M12 -> 1169.991 | O12: Business | P12: N | Q12: =IF(P12="Y",1,0) -> 0
A13: ORD-011 | B13: 45336 | C13: Feb | D13: Q1 | E13: Bob | F13: South | G13: Office Supplies | H13: Stapler | I13: 15 | J13: 8.99 | K13: 0 | L13: =I13*J13 -> 134.85 | M13: =L13*K13 -> 0 | N13: =L13-M13 -> 134.85 | O13: Retail | P13: N | Q13: =IF(P13="Y",1,0) -> 0
A14: ORD-012 | B14: 45340 | C14: Feb | D14: Q1 | E14: Eve | F14: North | G14: Electronics | H14: Tablet X | I14: 2 | J14: 499 | K14: 0.05 | L14: =I14*J14 -> 998 | M14: =L14*K14 -> 49.9 | N14: =L14-M14 -> 948.1 | O14: Business | P14: N | Q14: =IF(P14="Y",1,0) -> 0
... A42: ORD-040 | B42: 45457 | C42: Jun | D42: Q2 | E42: Dave | F42: West | G42: Electronics | H42: Smartphone Z | I42: 5 | J42: 899 | K42: 0.1 | L42: =I42*J42 -> 4495 | M42: =L42*K42 -> 449.5 | N42: =L42-M42 -> 4045.5 | O42: Business | P42: N | Q42: =IF(P42="Y",1,0) -> 0
A45: DATA CLEANING LOG
A46: Step | B46: Action Taken | C46: Column(s) Affected
A47: 1 | B47: Verified no duplicate OrderIDs | C47: OrderID (Col A)
A48: 2 | B48: Confirmed date format consistency (YYYY-MM-DD) | C48: Date (Col B)
A49: 3 | B49: Derived Month and Quarter from Date | C49: Month (Col C), Quarter (Col D)
A50: 4 | B50: Checked Units and UnitPrice for negatives / blanks — none found | C50: Units, UnitPrice
A51: 5 | B51: Discount validated to range 0–25% — all values within range | C51: Discount (Col K)
A52: 6 | B52: Calculated GrossSales = Units × UnitPrice | C52: GrossSales (Col L)
A53: 7 | B53: Calculated DiscountAmt = GrossSales × Discount | C53: DiscountAmt (Col M)
A54: 8 | B54: Calculated NetSales = GrossSales − DiscountAmt | C54: NetSales (Col N)
A55: 9 | B55: Created binary IsReturn flag (1=Yes, 0=No) | C55: IsReturn (Col Q)

Sheet Formulas & Functions
A1: 🔢 FORMULAS & FUNCTIONS SHOWCASE
A3: 📌 SECTION 1 — Aggregation Functions (Source: Cleaned Data col N = NetSales)
A4: Total Net Sales | B4: =SUM('Cleaned Data'!N3:N42) -> 57321.082 | C4: =SUM('Cleaned Data'!N3:N42) -> 57321.082 | D4: SUM: Adds all NetSales values
A5: Average Net Sales | B5: =AVERAGE('Cleaned Data'!N3:N42) -> 1433.027 | C5: =AVERAGE('Cleaned Data'!N3:N42) -> 1433.027 | D5: AVERAGE: Mean of all orders
A6: Maximum Order Value | B6: =MAX('Cleaned Data'!N3:N42) -> 4045.5 | C6: =MAX('Cleaned Data'!N3:N42) -> 4045.5 | D6: MAX: Largest single order
A7: Minimum Order Value | B7: =MIN('Cleaned Data'!N3:N42) -> 4 | C7: =MIN('Cleaned Data'!N3:N42) -> 4 | D7: MIN: Smallest single order
A8: Median Order Value | B8: =MEDIAN('Cleaned Data'!N3:N42) -> 1279.095 | C8: =MEDIAN('Cleaned Data'!N3:N42) -> 1279.095 | D8: MEDIAN: Middle value
A9: Order Count | B9: =COUNTA('Cleaned Data'!A3:A42) -> 40 | C9: =COUNTA('Cleaned Data'!A3:A42) -> 40 | D9: COUNTA: Non-blank cells
A11: 📌 SECTION 2 — Conditional Functions
A12: Electronics Revenue | B12: =SUMIF('Cleaned Data'!G3:G42,"Electronics",'Cleaned Data'!N3:N42) -> 42153.867 | C12: =SUMIF('Cleaned Data'!G3:G42,"Electronics",'Cleaned Data'!N3:N42) -> 42153.867 | D12: SUMIF: Sum where Category = Electronics
A13: North Region Revenue | B13: =SUMIF('Cleaned Data'!F3:F42,"North",'Cleaned Data'!N3:N42) -> 19255.589 | C13: =SUMIF('Cleaned Data'!F3:F42,"North",'Cleaned Data'!N3:N42) -> 19255.589 | D13: SUMIF: Sum where Region = North
A14: Business Customer Revenue | B14: =SUMIF('Cleaned Data'!O3:O42,"Business",'Cleaned Data'!N3:N42) -> 42896.353 | C14: =SUMIF('Cleaned Data'!O3:O42,"Business",'Cleaned Data'!N3:N42) -> 42896.353 | D14: SUMIF: Business customers only
A15: Alice's Total Sales | B15: =SUMIF('Cleaned Data'!E3:E42,"Alice",'Cleaned Data'!N3:N42) -> 10938.406 | C15: =SUMIF('Cleaned Data'!E3:E42,"Alice",'Cleaned Data'!N3:N42) -> 10938.406 | D15: SUMIF: Alice's contribution
A16: Electronics + North Revenue | B16: =SUMIFS('Cleaned Data'!N3:N42,'Cleaned Data'!G3:G42,"Electronics",'Cleaned Data'!F3:F42,"North") -> 14145.964 | C16: =SUMIFS('Cleaned Data'!N3:N42,'Cleaned Data'!G3:G42,"Electronics",'Cleaned Data'!F3:F42,"North") -> 14145.964 | D16: SUMIFS: Multiple criteria
A17: Count Electronics Orders | B17: =COUNTIF('Cleaned Data'!G3:G42,"Electronics") -> 19 | C17: =COUNTIF('Cleaned Data'!G3:G42,"Electronics") -> 19 | D17: COUNTIF: Number of Electronics orders
A18: Count Business Customers | B18: =COUNTIF('Cleaned Data'!O3:O42,"Business") -> 24 | C18: =COUNTIF('Cleaned Data'!O3:O42,"Business") -> 24 | D18: COUNTIF: Business customer count
A19: Count Returns | B19: =COUNTIF('Cleaned Data'!P3:P42,"Y") -> 3 | C19: =COUNTIF('Cleaned Data'!P3:P42,"Y") -> 3 | D19: COUNTIF: Orders flagged as returned
A21: 📌 SECTION 3 — Lookup & Reference Functions
D22: OrderID | E22: SalesRep | F22: NetSales
A23: Lookup Order: | B23: ORD-010
A24: Rep for ORD-010 | B24: =VLOOKUP(B23,'Cleaned Data'!A3:Q42,5,FALSE()) -> Dave | C24: =VLOOKUP(B23,'Cleaned Data'!A3:Q42,5,FALSE()) -> Dave | D24: VLOOKUP: Find SalesRep by OrderID
A25: NetSales for ORD-010 | B25: =VLOOKUP(B23,'Cleaned Data'!A3:Q42,14,FALSE()) -> 1169.991 | C25: =VLOOKUP(B23,'Cleaned Data'!A3:Q42,14,FALSE()) -> 1169.991 | D25: VLOOKUP: Return NetSales column (#14)
A26: Index/Match SalesRep | B26: =INDEX('Cleaned Data'!E3:E42,MATCH(B23,'Cleaned Data'!A3:A42,0)) -> Dave | C26: =INDEX('Cleaned Data'!E3:E42,MATCH(B23,'Cleaned Data'!A3:A42,0)) -> Dave | D26: INDEX+MATCH: More flexible alternative to VLOOKUP
A28: 📌 SECTION 4 — Text & Date Functions
A29: Sample Order Date (A42 of raw): | B29: ='Cleaned Data'!B42 -> 45457
A30: Year of last order | B30: =YEAR(B29) -> 2024 | C30: =YEAR(B29) -> 2024 | D30: YEAR: Extract year from date
A31: Month number | B31: =MONTH(B29) -> 6 | C31: =MONTH(B29) -> 6 | D31: MONTH: Extract month number
A32: Formatted date text | B32: =TEXT(B29,"MMMM DD, YYYY") -> June 14, 2024 | C32: =TEXT(B29,"MMMM DD, YYYY") -> June 14, 2024 | D32: TEXT: Format a date as readable string
A33: Days since first order | B33: =B29-'Cleaned Data'!B3 -> 161 | C33: =B29-'Cleaned Data'!B3 -> 161 | D33: Date subtraction: elapsed days
A35: Concatenate Rep + Region | B35: =CONCATENATE('Cleaned Data'!E3," — ",'Cleaned Data'!F3) -> Alice — North | C35: =CONCATENATE('Cleaned Data'!E3," — ",'Cleaned Data'!F3) -> Alice — North | D35: CONCAT: Join strings
A36: Upper-case product name | B36: =UPPER('Cleaned Data'!H3) -> LAPTOP PRO | C36: =UPPER('Cleaned Data'!H3) -> LAPTOP PRO | D36: UPPER: Convert text to uppercase
A38: 📌 SECTION 5 — Logical & IF Functions
A39: High-value order? (>$2000) | B39: =IF('Cleaned Data'!N3>2000,"High Value","Standard") -> High Value | C39: =IF('Cleaned Data'!N3>2000,"High Value","Standard") -> High Value | D39: IF: Classify order by size
A40: Revenue tier (IFS) | B40: =IF('Cleaned Data'!N3>=2000,"Premium",IF('Cleaned Data'!N3>=500,"Standard","Budget")) -> Premium | C40: =IF('Cleaned Data'!N3>=2000,"Premium",IF('Cleaned Data'!N3>=500,"Standard","Budget")) -> Premium | D40: IFS: Multi-level classification
A41: Electronics & Business? | B41: =AND('Cleaned Data'!G3="Electronics",'Cleaned Data'!O3="Business") -> TRUE | C41: =AND('Cleaned Data'!G3="Electronics",'Cleaned Data'!O3="Business") -> TRUE | D41: AND: Both conditions must be TRUE
A42: Return rate % | B42: =COUNTIF('Cleaned Data'!P3:P42,"Y")/COUNTA('Cleaned Data'!A3:A42) -> 0.075 | C42: =COUNTIF('Cleaned Data'!P3:P42,"Y")/COUNTA('Cleaned Data'!A3:A42) -> 0.075 | D42: Compound formula: % of returns

Sheet Pivot Analysis
A1: 📋 PIVOT TABLE ANALYSIS — Summary Tables by Key Dimensions
A3: PIVOT 1 — Revenue by Category | G3: PIVOT 2 — Revenue by Region
A4: Category | B4: Gross Sales | C4: Net Sales | D4: % of Total | G4: Region | H4: Orders | I4: Net Sales | J4: Avg per Order
A5: Electronics | B5: =SUMIF('Cleaned Data'!G3:G42,A5,'Cleaned Data'!L3:L42) -> 44702.73 | C5: =SUMIF('Cleaned Data'!G3:G42,A5,'Cleaned Data'!N3:N42) -> 42153.867 | D5: =C5/SUM(C5:C7) -> 0.73539901 | G5: North | H5: =COUNTIF('Cleaned Data'!F3:F42,G5) -> 16 | I5: =SUMIF('Cleaned Data'!F3:F42,G5,'Cleaned Data'!N3:N42) -> 19255.589 | J5: =I5/H5 -> 1203.4743
A6: Furniture | B6: =SUMIF('Cleaned Data'!G3:G42,A6,'Cleaned Data'!L3:L42) -> 14491.5 | C6: =SUMIF('Cleaned Data'!G3:G42,A6,'Cleaned Data'!N3:N42) -> 13318.5 | D6: =C6/SUM(C5:C7) -> 0.23234907 | G6: South | H6: =COUNTIF('Cleaned Data'!F3:F42,G6) -> 8 | I6: =SUMIF('Cleaned Data'!F3:F42,G6,'Cleaned Data'!N3:N42) -> 11345.924 | J6: =I6/H6 -> 1418.2405
A7: Office Supplies | B7: =SUMIF('Cleaned Data'!G3:G42,A7,'Cleaned Data'!L3:L42) -> 1990.8 | C7: =SUMIF('Cleaned Data'!G3:G42,A7,'Cleaned Data'!N3:N42) -> 1848.715 | D7: =C7/SUM(C5:C7) -> 0.032251921 | G7: East | H7: =COUNTIF('Cleaned Data'!F3:F42,G7) -> 8 | I7: =SUMIF('Cleaned Data'!F3:F42,G7,'Cleaned Data'!N3:N42) -> 12756.195 | J7: =I7/H7 -> 1594.5244
A8: TOTAL | B8: =SUM(B5:B7) -> 61185.03 | C8: =SUM(C5:C7) -> 57321.082 | D8: =SUM(D5:D7) -> 1 | G8: West | H8: =COUNTIF('Cleaned Data'!F3:F42,G8) -> 8 | I8: =SUMIF('Cleaned Data'!F3:F42,G8,'Cleaned Data'!N3:N42) -> 13963.373 | J8: =I8/H8 -> 1745.4216
G9: TOTAL | H9: =SUM(H5:H8) -> 40 | I9: =SUM(I5:I8) -> 57321.082 | J9: =I9/H9 -> 1433.027
A11: PIVOT 3 — Sales Rep Performance | G11: PIVOT 4 — Monthly Revenue Trend
A12: Sales Rep | B12: Orders | C12: Gross Sales | D12: Net Sales | E12: Discount Given | G12: Month | H12: Orders | I12: Net Sales | J12: MoM Change | K12: Cum. Sales
A13: Alice | B13: =COUNTIF('Cleaned Data'!E3:E42,A13) -> 9 | C13: =SUMIF('Cleaned Data'!E3:E42,A13,'Cleaned Data'!L3:L42) -> 11210.48 | D13: =SUMIF('Cleaned Data'!E3:E42,A13,'Cleaned Data'!N3:N42) -> 10938.406 | E13: =C13-D13 -> 272.074 | G13: Jan | H13: =COUNTIF('Cleaned Data'!C3:C42,G13) -> 7 | I13: =SUMIF('Cleaned Data'!C3:C42,G13,'Cleaned Data'!N3:N42) -> 10801.206 | J13: — | K13: =I13 -> 10801.206
A14: Bob | B14: =COUNTIF('Cleaned Data'!E3:E42,A14) -> 8 | C14: =SUMIF('Cleaned Data'!E3:E42,A14,'Cleaned Data'!L3:L42) -> 12092.07 | D14: =SUMIF('Cleaned Data'!E3:E42,A14,'Cleaned Data'!N3:N42) -> 11345.924 | E14: =C14-D14 -> 746.146 | G14: Feb | H14: =COUNTIF('Cleaned Data'!C3:C42,G14) -> 7 | I14: =SUMIF('Cleaned Data'!C3:C42,G14,'Cleaned Data'!N3:N42) -> 9944.284 | J14: =(I14-I13)/I13 -> -0.07933577 | K14: =K13+I14 -> 20745.49
A15: Carol | B15: =COUNTIF('Cleaned Data'!E3:E42,A15) -> 8 | C15: =SUMIF('Cleaned Data'!E3:E42,A15,'Cleaned Data'!L3:L42) -> 13544.05 | D15: =SUMIF('Cleaned Data'!E3:E42,A15,'Cleaned Data'!N3:N42) -> 12756.195 | E15: =C15-D15 -> 787.8546 | G15: Mar | H15: =COUNTIF('Cleaned Data'!C3:C42,G15) -> 7 | I15: =SUMIF('Cleaned Data'!C3:C42,G15,'Cleaned Data'!N3:N42) -> 8530.8439 | J15: =(I15-I14)/I14 -> -0.14213593 | K15: =K14+I15 -> 29276.334
A16: Dave | B16: =COUNTIF('Cleaned Data'!E3:E42,A16) -> 8 | C16: =SUMIF('Cleaned Data'!E3:E42,A16,'Cleaned Data'!L3:L42) -> 15354.47 | D16: =SUMIF('Cleaned Data'!E3:E42,A16,'Cleaned Data'!N3:N42) -> 13963.373 | E16: =C16-D16 -> 1391.097 | G16: Apr | H16: =COUNTIF('Cleaned Data'!C3:C42,G16) -> 8 | I16: =SUMIF('Cleaned Data'!C3:C42,G16,'Cleaned Data'!N3:N42) -> 11301.495 | J16: =(I16-I15)/I15 -> 0.32478045 | K16: =K15+I16 -> 40577.829
A17: Eve | B17: =COUNTIF('Cleaned Data'!E3:E42,A17) -> 7 | C17: =SUMIF('Cleaned Data'!E3:E42,A17,'Cleaned Data'!L3:L42) -> 8983.96 | D17: =SUMIF('Cleaned Data'!E3:E42,A17,'Cleaned Data'!N3:N42) -> 8317.1832 | E17: =C17-D17 -> 666.7768 | G17: May | H17: =COUNTIF('Cleaned Data'!C3:C42,G17) -> 7 | I17: =SUMIF('Cleaned Data'!C3:C42,G17,'Cleaned Data'!N3:N42) -> 9563.8425 | J17: =(I17-I16)/I16 -> -0.15375423 | K17: =K16+I17 -> 50141.672
A18: TOTAL | B18: =SUM(B13:B17) -> 40 | C18: =SUM(C13:C17) -> 61185.03 | D18: =SUM(D13:D17) -> 57321.082 | E18: =SUM(E13:E17) -> 3863.9484 | G18: Jun | H18: =COUNTIF('Cleaned Data'!C3:C42,G18) -> 4 | I18: =SUMIF('Cleaned Data'!C3:C42,G18,'Cleaned Data'!N3:N42) -> 7179.41 | J18: =(I18-I17)/I17 -> -0.24931742 | K18: =K17+I18 -> 57321.082
A20: PIVOT 5 — Category × Customer Type
A21: Category | B21: Business $ | C21: Retail $ | D21: Total | E21: Bus %
A22: Electronics | B22: =SUMIFS('Cleaned Data'!N3:N42,'Cleaned Data'!G3:G42,A22,'Cleaned Data'!O3:O42,"Business") -> 33270.753 | C22: =SUMIFS('Cleaned Data'!N3:N42,'Cleaned Data'!G3:G42,A22,'Cleaned Data'!O3:O42,"Retail") -> 8883.114 | D22: =B22+C22 -> 42153.867 | E22: =B22/D22 -> 0.7892693
A23: Furniture | B23: =SUMIFS('Cleaned Data'!N3:N42,'Cleaned Data'!G3:G42,A23,'Cleaned Data'!O3:O42,"Business") -> 9614.1 | C23: =SUMIFS('Cleaned Data'!N3:N42,'Cleaned Data'!G3:G42,A23,'Cleaned Data'!O3:O42,"Retail") -> 3704.4 | D23: =B23+C23 -> 13318.5 | E23: =B23/D23 -> 0.72186057
A24: Office Supplies | B24: =SUMIFS('Cleaned Data'!N3:N42,'Cleaned Data'!G3:G42,A24,'Cleaned Data'!O3:O42,"Business") -> 11.5 | C24: =SUMIFS('Cleaned Data'!N3:N42,'Cleaned Data'!G3:G42,A24,'Cleaned Data'!O3:O42,"Retail") -> 1837.215 | D24: =B24+C24 -> 1848.715 | E24: =B24/D24 -> 0.006220537
A25: TOTAL | B25: =SUM(B22:B24) -> 42896.353 | C25: =SUM(C22:C24) -> 14424.729 | D25: =SUM(D22:D24) -> 57321.082 | E25: =B25/D25 -> 0.74835211

Sheet Data Visualizations
A1: 📈 DATA VISUALIZATIONS
A2: Chart 1 — Net Sales by Category | I2: Chart 2 — Net Sales by Sales Rep
A21: Chart 3 — Monthly Revenue Trend | I21: Chart 4 — Regional Revenue Share

Sheet Insights Dashboard
A1: 📊 EXECUTIVE INSIGHTS DASHBOARD | Sales Performance 2024 Q1–Q2
B3: TOTAL NET SALES | D3: TOTAL ORDERS | F3: AVG ORDER VALUE | H3: RETURN RATE | J3: TOP CATEGORY
B4: =SUM('Cleaned Data'!N3:N42) -> 57321.082 | D4: =COUNTA('Cleaned Data'!A3:A42) -> 40 | F4: =SUM('Cleaned Data'!N3:N42)/COUNTA('Cleaned Data'!A3:A42) -> 1433.027 | H4: =COUNTIF('Cleaned Data'!P3:P42,"Y")/COUNTA('Cleaned Data'!A3:A42) -> 0.075 | J4: =INDEX('Pivot Analysis'!A5:A7,MATCH(MAX('Pivot Analysis'!C5:C7),'Pivot Analysis'!C5:C7,0)) -> Electronics
B7: KEY FINDINGS & BUSINESS INSIGHTS
B8: 🏆 Top Revenue Category
B9: Electronics dominates with the highest net sales, driven by high unit prices (Laptop Pro $1,300, Smartphone $899). This segment represents the core revenue engine.
B10: 📍 Regional Performance
B11: The North region leads in order count due to Alice and Eve's combined presence. The West and South show opportunity for growth through increased rep coverage.
B12: 👥 Sales Rep Insights
B13: Alice consistently generates high-value orders by focusing on Electronics and Business customers. Dave in the West shows strong unit volume with competitive discounting.
B14: 📅 Monthly Trend
B15: Revenue shows a positive growth trend from Q1 to Q2, with May being the peak month. The Jan–Feb period had lower volume, likely seasonal effects.
B16: 💼 Customer Segmentation
B17: Business customers account for the majority of Electronics revenue, while Retail customers are more active in Office Supplies. Targeted pricing strategies by segment are recommended.
B18: ⚠️ Return Risk
... B25: ℹ️ Conditional Formatting applied in 'Cleaned Data' sheet: Color scale on Net Sales column (N) — Green=High, Red=Low
